signalwire_pom/__init__.py
signalwire_pom/__main__.py
signalwire_pom/pom.py
signalwire_pom/pom_tool.py
signalwire_pom/win_install.py
signalwire_pom-2.7.2.dist-info/licenses/LICENSE
signalwire_pom-2.7.2.dist-info/METADATA
signalwire_pom-2.7.2.dist-info/WHEEL
signalwire_pom-2.7.2.dist-info/entry_points.txt
signalwire_pom-2.7.2.dist-info/top_level.txt
signalwire_pom-2.7.2.dist-info/RECORD
