Metadata-Version: 2.4
Name: signalwire-pom
Version: 2.7.2
Summary: Prompt Object Model - A structured data format for organizing and rendering LLM prompts
Author-email: SignalWire <support@signalwire.com>
License-Expression: MIT
Project-URL: Homepage, https://github.com/briankwest/signalwire-pom
Project-URL: Issues, https://github.com/briankwest/signalwire-pom/issues
Classifier: Programming Language :: Python :: 3
Classifier: Operating System :: OS Independent
Requires-Python: >=3.6
License-File: LICENSE
Requires-Dist: docopt
Requires-Dist: pyyaml
Dynamic: license-file
